bigdl/share/tflibs/linux-x86_64/libiomp5.so
bigdl/share/tflibs/linux-x86_64/libmklml_intel.so
bigdl_math-2.3.0.dist-info/METADATA
bigdl_math-2.3.0.dist-info/WHEEL
bigdl_math-2.3.0.dist-info/top_level.txt
bigdl_math-2.3.0.dist-info/RECORD
