Metadata-Version: 2.1
Name: bigdl-math
Version: 2.3.0
Summary: Math Dependency Library for bigdl-orca
Home-page: https://github.com/intel-analytics/BigDL
Author: BigDL Authors
Author-email: bigdl-user-group@googlegroups.com
License: Apache License, Version 2.0
Platform: UNKNOWN
